{"d":{"__type":"AspDotNetStorefront.AutocompleteResult","Terms":[],"Categories":[{"EntityType":"category","Name":"Freeze Dried Cat Treats","ParentName":"Pet Care","Url":"/c-14775-freeze-dried-cat-treats"},{"EntityType":"category","Name":"Cats Claw","ParentName":"Herbs","Url":"/c-223-cats-claw"},{"EntityType":"category","Name":"Canned Cat Food","ParentName":"Pet Care","Url":"/c-1789-canned-cat-food"},{"EntityType":"category","Name":"Freeze Dried Cat Food","ParentName":"Pet Care","Url":"/c-14741-freeze-dried-cat-food"},{"EntityType":"category","Name":"Catuaba","ParentName":"Men\u0027s Health","Url":"/c-2086-catuaba"}],"Brands":[{"EntityType":"manufacturer","Name":"Safe Catch","ParentName":"","Url":"/m-10398-safe-catch"},{"EntityType":"manufacturer","Name":"Catherine Malandrino","ParentName":"","Url":"/m-14528-catherine-malandrino"}],"Translations":{}}}
